{
    "url": "https://writing9.com/text/619657d1b70763001987327e-a-museum-near-your-home-is-looking-for-people-to",
    "file": [
        "data",
        "9",
        "619657d1b70763001987327e.json"
    ],
    "topics": [
        "museum",
        "home",
        "people",
        "work",
        "director",
        "skills",
        "qualities"
    ],
    "question": "A museum near your home is looking for people to do part-time voluntary/unpaid work. You would like to do some voluntary/unpaid work at the museum. Write a letter to the museum director to apply for the voluntary/unpaid work. In your letter explain why you want to do voluntary/unpaid work at the museum, describe some skills and qualities you have that would be useful and give details of when you would be available to work.",
    "scores": {
        "overall_band_score": 9.0,
        "coherence_and_cohesion": {
            "overall_score": 9.0,
            "structure_your_answers_in_logical_paragraphs": 9.0,
            "one_main_idea_per_paragraph": 9.0,
            "include_greeting_and_closing": 9.0,
            "use_cohesive_linking_words_accurately_and_appropriately": 9.0,
            "vary_your_linking_phrases_using_synonyms": 9.0
        },
        "lexical_resource": {
            "overall_score": 9.0,
            "try_to_vary_your_vocabulary_using_accurate_synonyms": 9.0,
            "check_your_work_for_spelling_and_word_formation_mistakes": 9.0
        },
        "grammatical_range": {
            "overall_score": 9.0,
            "use_a_variety_of_complex_and_simple_sentences": 9.0,
            "check_your_writing_for_errors": 9.0
        },
        "task_achievement": {
            "overall_score": 9.0,
            "answer_all_parts_of_the_question": 9.0,
            "use_an_appropriate_tone": 9.0,
            "word_count": 0.0
        }
    },
    "text": [
        "Dear Sir or Madam",
        "I am writing this letter to express my interest to work part-time in the museum.I was informed by the recruitment agency that you are looking to hire part-time employees.It could be great if I am considered for the position once you have gone through my details.",
        "My name is Rehana and currently,I am pursuing a degree in arts at the University of Hyderabad.The experience gained from this work will help  me in completing my thesis,which is on Persian art,displayed in the museum.I will also gain valuable guidance from famous curators of your museum.",
        "I have done diploma in assessing the timeline of ancient relics from the University of Delhi.I can work in the ancient relics department along with your regular staff to help handle the work.I am a hard-working and disciplined person,and I am a great team player too.Additionally,I can give counselling to budding artists.",
        "I have  my mid-term exams till the 24th of March,after which I will be available .I am free from morning  till late afternoon;however,I am busy in the evenings as I have a  summer project to finish.I will be able to volunteer for 30 days,after which my semester starts and it could be difficult to balance my workload and a part-time job.",
        "Thank you for your consideration.",
        "Yours faithfully",
        "Rehana"
    ],
    "errors": {
        "num_error": "0",
        "error_list": []
    },
    "submitter": "rehanafees",
    "num_words": 218,
    "num_paragraphs": 8,
    "linking_words": {
        "num_linking_words": "4",
        "list_linking_words": [
            "also",
            "additionally",
            "however",
            "this"
        ]
    },
    "repeated_words": {
        "num_repeated_words": "1",
        "list_repeated_words": [
            {
                "word": "work",
                "occurrences": [
                    {
                        "start_idx": 69,
                        "end_idx": 73
                    },
                    {
                        "start_idx": 407,
                        "end_idx": 411
                    },
                    {
                        "start_idx": 669,
                        "end_idx": 673
                    },
                    {
                        "start_idx": 756,
                        "end_idx": 760
                    },
                    {
                        "start_idx": 773,
                        "end_idx": 777
                    },
                    {
                        "start_idx": 1202,
                        "end_idx": 1206
                    }
                ]
            }
        ]
    },
    "datetime_submitted": "2021-11-18T13:42:01.584Z"
}