{
    "url": "https://thanhnien.vn/chien-su-ngay-115-tong-thong-ukraine-den-thanh-pho-mykolaiv-post1469920.html",
    "file": [
        "data",
        "2022",
        "1469920.json"
    ],
    "title": "Chiến sự ngày 115: Tổng thống Ukraine đến thành phố Mykolaiv",
    "datetime": "2022-06-19T05:08:00+0700",
    "author": "Khánh An",
    "abstract": "Tổng thống Ukraine Volodymyr Zelensky lần đầu đến thành phố Mykolaiv ở miền nam kể từ khi Nga đưa quân sang.",
    "content": "Hãng AFP ngày 18.6 đưa tin Tổng thống Ukraine Volodymyr Zelensky đến thăm thành phố Mykolaiv ở miền nam, thị sát tình hình thiệt hại do chiến sự và tham dự cuộc họp với giới chức địa phương. \nChuyến đi của ông diễn ra 1 ngày sau khi phía Ukraine cho hay Nga không kích tại thành phố này khiến 2 người thiệt mạng và 20 người bị thương. Nga chưa bình luận thông tin này. Mykolaiv là mục tiêu của lực lượng Nga kể từ đầu chiến dịch do nằm trên đường đến thành phố cảng chiến lược Odessa.\nNhững hình ảnh cho thấy Tổng thống Zelensky đến một tòa nhà dân cư bị thiệt hại cùng tỉnh trưởng Mykolaiv Vitaliy Kim.\nÔng còn đến thăm một bệnh viện và dự họp với giới chức địa phương tại một nơi trông giống như tầng hầm, nơi ông trao thưởng cho các binh sĩ. Văn phòng Tổng thống Ukraine ra thông cáo cho hay ông đã thảo luận về tình hình kinh tế, khôi phục nguồn cung nước và tình hình nông nghiệp. \n“Sự chú ý đặc biệt đối với những mối đe dọa trên bộ và trên biển. Chúng tôi không ngừng làm việc vì chiến thắng”, theo thông cáo.\nTheo tờ The Washington Post, một quan chức quốc phòng Mỹ ngày 17.6 xác nhận lực lượng Ukraine đã tấn công một tàu kéo thuộc hải quân Nga bằng ít nhất 1 tên lửa diệt hạm Harpoon do Mỹ chế tạo. Cuộc tấn công diễn ra ở biển Đen gần đảo Rắn, một vị trí chiến lược đang bị lực lượng Nga kiểm soát.\nTrước đó, Reuters đưa tin hải quân Ukraine tuyên bố lực lượng này đã tấn công một tàu kéo của hải quân Nga bằng hai tên lửa Harpoon ở biển Đen. Tàu kéo này được xác định là Vasiliy Bekh, chở binh sĩ, vũ khí và đạn dược đến đảo Rắn, theo hải quân Ukraine.\nĐây là lần đầu tiên Ukraine tuyên bố đã dùng tên lửa diệt hạm do phương Tây cung cấp để tấn công một tàu Nga. Hiện chưa có thông tin về phản ứng của Nga.\nXem thêm: Quan chức Mỹ xác nhận Ukraine tấn công tàu hải quân Nga bằng tên lửa Harpoon\nMột sĩ quan lực lượng dân quân thân Nga tại tỉnh Luhansk ở miền đông Ukraine hôm 17.6 cho biết một số binh sĩ Ukraine cố thủ trong nhà máy Azot ở thành phố Severodonetsk đã ra hàng.\nTheo hãng tin TASS, sĩ quan Andrey Marochko không tiết lộ số người đầu hàng và đơn vị cụ thể của họ với lý do an ninh. Ông nói rằng Ukraine đang triển khai những đơn vị ngăn chặn binh lính rút quân hoặc ra hàng.\nTrước đó, TASS đưa tin có đến 2.500 binh sĩ, mà 1/4 trong số này được cho là lính đánh thuê nước ngoài, có thể đang cố thủ ở nhà máy Azot.\nPhe ly khai “Cộng hòa Nhân dân Luhansk” (LPR) tự xưng cáo buộc các binh lính Ukraine đang bắt giữ 1.200 dân thường làm con tin trong nhà máy. Ukraine bác bỏ cáo buộc này.\nLực lượng dân quân của LPR đã nhiều lần kêu gọi binh lính Ukraine ở Severodonetsk ra hàng. Moscow cam kết sẽ đảm bảo mạng sống cho các tù binh và tuân thủ Công ước Geneva về cách đối xử với tù binh, như trường hợp các tù binh ở Mariupol.\nTheo Reuters dẫn lời tỉnh trưởng Luhansk Serhiy Gaidai, Nga đang điều một lượng lớn binh sĩ dự bị từ các khu vực chiến sự khác đến nhằm kiểm soát hoàn toàn Severodonetsk. Ông cho biết lực lượng Nga hiện đã kiểm soát hầu hết, nhưng không phải toàn bộ thành phố.\nXem thêm: Nhiều binh sĩ Ukraine ra hàng tại Severodonetsk, Nga nối lại hoạt động quân sự gần Izium\nQuan chức phụ trách chính sách ngoại giao của Liên minh châu Âu (EU) Josep Borrell cho rằng Nga đã khiến thế giới có nguy cơ bị đói, thông qua việc phong tỏa các chuyến tàu chở ngũ cốc của Ukraine, cũng như việc Nga giới hạn xuất khẩu.\n“Chúng tôi sẵn sàng phối hợp với Liên Hiệp Quốc và các đối tác nhằm phòng ngừa bất cứ tác động không mong muốn nào đối với an ninh lương thực toàn cầu”, ông viết trên trang web cá nhân.\nQuan chức này chỉ trích Nga lựa chọn “vũ khí hóa” xuất khẩu ngũ cốc và dùng nó làm công cụ gây áp lực với “bất cứ bên nào phản đối sự hung hăng của họ”.\nÔng cho biết các lệnh cấm vận của EU không cấm Nga xuất khẩu bất cứ hàng hóa nông nghiệp nào cũng như thanh toán cho các khoản xuất khẩu đó.\nTrong khi đó, hãng TASS dẫn lời Tổng thống Nga Vladimir Putin cho rằng hành động của phương Tây nhằm vào kinh tế Nga đã thất bại. Ông chỉ ra rằng giới chính trị gia châu Âu phải xoay xở tìm cách đối phó với tác động kinh tế đối với nước của họ.\nTổng thống Nga Vladimir Putin ngày 17.6 cho biết Nga \"không phản đối\" việc Ukraine có thể trở thành thành viên Liên minh châu Âu.\n\"Chúng tôi không phản đối điều đó. Họ có chủ quyền quyết định có tham gia các liên minh kinh tế hay không. Đó là việc của họ, việc của người dân Ukraine\", ông Putin nói tại Diễn đàn Kinh tế Quốc tế St.Petersburg.\nPhát biểu này được đưa ra sau khi Ủy ban châu Âu ngày 17.6 đề nghị cấp cho Ukraine tư cách ứng viên của Liên minh châu Âu. Tuy nhiên, ông Putin cho biết ông tin rằng nếu Ukraine tiếp tục gia nhập EU, nước này sẽ \"biến thành một nửa thuộc địa\" của các nước phương Tây.\nXem thêm: Ủng hộ Ukraine, nhưng châu Âu không chuyển thêm vũ khí hạng nặng",
    "tags": [
        "Ukraine",
        "Chiến Sự",
        "Nhà Máy Azot",
        "Vasiliy Bekh",
        "Andrey Marochko",
        "Đảo Rắn",
        "Tàu Kéo",
        "Hải Quân Ukraine",
        "Luhansk Serhiy Gaidai",
        "Hải Quân Nga"
    ]
}